pyshredder/__init__.py
pyshredder/core/__init__.py
pyshredder/core/eraser.py
pyshredder/util/__init__.py
pyshredder/util/shredder.py
pyshredder-0.1.4.dist-info/METADATA
pyshredder-0.1.4.dist-info/WHEEL
pyshredder-0.1.4.dist-info/top_level.txt
pyshredder-0.1.4.dist-info/RECORD
